pepbrowser/__init__.py
pepbrowser/__main__.py
pepbrowser/cli.py
pepbrowser/core.py
pepbrowser-0.2.0.dist-info/LICENSE
pepbrowser-0.2.0.dist-info/METADATA
pepbrowser-0.2.0.dist-info/WHEEL
pepbrowser-0.2.0.dist-info/entry_points.txt
pepbrowser-0.2.0.dist-info/top_level.txt
pepbrowser-0.2.0.dist-info/RECORD
